mumott/__init__.py
mumott/core/__init__.py
mumott/core/cuda_kernels.py
mumott/core/cuda_utils.py
mumott/core/deprecation_warning.py
mumott/core/geometry.py
mumott/core/hashing.py
mumott/core/john_transform.py
mumott/core/john_transform_cuda.py
mumott/core/john_transform_sparse_cuda.py
mumott/core/numba_setup.py
mumott/core/probed_coordinates.py
mumott/core/projection_stack.py
mumott/core/simulator.py
mumott/core/spherical_harmonic_mapper.py
mumott/core/wigner_d_matrices.h5
mumott/core/wigner_d_utilities.py
mumott/data_handling/__init__.py
mumott/data_handling/data_container.py
mumott/data_handling/utilities/__init__.py
mumott/data_handling/utilities/data_processing.py
mumott/methods/__init__.py
mumott/methods/basis_sets/__init__.py
mumott/methods/basis_sets/base_basis_set.py
mumott/methods/basis_sets/gaussian_kernels.py
mumott/methods/basis_sets/nearest_neighbor.py
mumott/methods/basis_sets/spherical_harmonics.py
mumott/methods/basis_sets/trivial_basis.py
mumott/methods/projectors/__init__.py
mumott/methods/projectors/base_projector.py
mumott/methods/projectors/saxs_projector.py
mumott/methods/projectors/saxs_projector_cuda.py
mumott/methods/residual_calculators/__init__.py
mumott/methods/residual_calculators/base_residual_calculator.py
mumott/methods/residual_calculators/gradient_residual_calculator.py
mumott/methods/residual_calculators/zonal_harmonic_gradient_calculator.py
mumott/methods/utilities/__init__.py
mumott/methods/utilities/fiber_fit.py
mumott/methods/utilities/grids_on_the_sphere.py
mumott/methods/utilities/preconditioning.py
mumott/methods/utilities/tensor_operations.py
mumott/optimization/__init__.py
mumott/optimization/loss_functions/__init__.py
mumott/optimization/loss_functions/base_loss_function.py
mumott/optimization/loss_functions/huber_loss.py
mumott/optimization/loss_functions/squared_loss.py
mumott/optimization/optimizers/__init__.py
mumott/optimization/optimizers/base_optimizer.py
mumott/optimization/optimizers/gradient_descent.py
mumott-2.2.dist-info/licenses/LICENSE
mumott-2.2.dist-info/METADATA
mumott-2.2.dist-info/WHEEL
mumott-2.2.dist-info/top_level.txt
mumott-2.2.dist-info/RECORD
