Metadata-Version: 2.4
Name: mumott
Version: 2.2
Summary: A library for the analysis of multi-modal tensor tomography data
Maintainer: The mumott developers team
License-Expression: MPL-2.0
Project-URL: Homepage, https://mumott.org/
Project-URL: repository, https://gitlab.com/liebi-group/software/mumott
Classifier: Development Status :: 5 - Production/Stable
Classifier: Intended Audience :: Science/Research
Classifier: Operating System :: OS Independent
Classifier: Programming Language :: Python :: 3
Classifier: Programming Language :: Python :: 3 :: Only
Classifier: Programming Language :: Python :: 3.10
Classifier: Programming Language :: Python :: 3.11
Classifier: Programming Language :: Python :: 3.12
Classifier: Programming Language :: Python :: 3.13
Classifier: Topic :: Scientific/Engineering :: Chemistry
Classifier: Topic :: Scientific/Engineering :: Image Processing
Classifier: Topic :: Scientific/Engineering :: Physics
Classifier: Topic :: Scientific/Engineering :: Visualization
License-File: LICENSE
Requires-Dist: colorcet
Requires-Dist: colorspacious
Requires-Dist: matplotlib!=3.9.0
Requires-Dist: h5py
Requires-Dist: cuda-core
Requires-Dist: cuda-bindings
Requires-Dist: numba-cuda
Requires-Dist: numpy>=1.23.3
Requires-Dist: scipy
Requires-Dist: scikit-image>=0.22
Requires-Dist: tqdm
Dynamic: license-file
